.mina/twilight.toml
avilla/twilight/__init__.py
avilla/twilight/base.py
avilla/twilight/commander_util.py
avilla/twilight/twilight.py
avilla/twilight/typing.py
avilla/twilight/util.py
avilla_twilight-0.3.1.dist-info/METADATA
avilla_twilight-0.3.1.dist-info/WHEEL
avilla_twilight-0.3.1.dist-info/licenses/LICENSE
avilla_twilight-0.3.1.dist-info/RECORD
