Metadata-Version: 2.1
Name: avilla-twilight
Version: 0.3.1
Summary: Twilight Message Parser for Avilla
Home-page: https://github.com/GraiaProject/Avilla
Author-Email: GreyElaina <GreyElaina@outlook.com>, BlueGlassBlock <blueglassblock@outlook.com>, ProgramRipper <programripper@foxmail.com>, RF-Tar-Railt <rf_tar_railt@qq.com>
License: AGPL-3.0
Project-URL: Homepage, https://github.com/GraiaProject/Avilla
Project-URL: Repository, https://github.com/GraiaProject/Avilla
Requires-Python: >=3.9
Requires-Dist: avilla-core>=1.0.0a8
Requires-Dist: pydantic>=1.10.0
